automategit/__init__.py
automategit/checkcredentials.py
automategit/clone_repo.py
automategit/create_repo.py
automategit/delete_repo.py
automategit/fetch_clean_create_repo.py
automategit-1.2.0.dist-info/LICENSE.txt
automategit-1.2.0.dist-info/METADATA
automategit-1.2.0.dist-info/WHEEL
automategit-1.2.0.dist-info/dependency_links.txt
automategit-1.2.0.dist-info/top_level.txt
automategit-1.2.0.dist-info/RECORD
