Metadata-Version: 2.1
Name: automategit
Version: 1.2.0
Summary: Github automation using python
Home-page: UNKNOWN
Author: Anukrati Rawal
Author-email: anukratirawal1.4@gmail.com
License: MIT
Platform: UNKNOWN
Classifier: License :: OSI Approved :: MIT License
Classifier: Programming Language :: Python :: 3.6
Classifier: Programming Language :: Python :: 3.7
Classifier: Programming Language :: Python :: 3.8
Requires-Dist: PyGithub (==1.53)
Requires-Dist: requests (==2.24.0)
